bhakti/__init__.py
bhakti/bootstrap/__init__.py
bhakti/bootstrap/bhakti_server.py
bhakti/client/__init__.py
bhakti/client/bhakti_client.py
bhakti/client/bhakti_reactive_client.py
bhakti/client/simple_reactive_client.py
bhakti/const/__init__.py
bhakti/const/bhakti_logo.py
bhakti/database/__init__.py
bhakti/database/db_engine.py
bhakti/exception/__init__.py
bhakti/exception/bhakti_connection_refused_error.py
bhakti/exception/bhakti_read_timeout_error.py
bhakti/exception/bhakti_remote_error.py
bhakti/exception/engine_not_support_error.py
bhakti/handler/__init__.py
bhakti/handler/dipamkara_handler.py
bhakti/handler/exception_notifier.py
bhakti/handler/inbound_data_log.py
bhakti/handler/str_data_trim.py
bhakti/handler/str_decoder.py
bhakti/handler/str_encoder.py
bhakti/server/__init__.py
bhakti/server/nio_server.py
bhakti/server/pipeline.py
bhakti/util/__init__.py
bhakti/util/async_repeat.py
bhakti/util/async_run.py
bhakti/util/func_timer.py
bhakti/util/logger.py
bhakti/util/readsuntil.py
bhakti/util/timeout.py
bhakti-0.2.19.dist-info/LICENSE
bhakti-0.2.19.dist-info/METADATA
bhakti-0.2.19.dist-info/WHEEL
bhakti-0.2.19.dist-info/entry_points.txt
bhakti-0.2.19.dist-info/top_level.txt
bhakti-0.2.19.dist-info/RECORD
