Metadata-Version: 2.1
Name: bhakti
Version: 0.2.19
Summary: An easy-to-use vector database.
Home-page: https://github.com/vortezwohl/Bhakti
Author: vortezwohl
Author-email: vortez.wohl@gmail.com
License: GNU GENERAL PUBLIC LICENSE
Project-URL: Bug Tracker, https://github.com/vortezwohl/Bhakti/issues
Classifier: Programming Language :: Python :: 3
Classifier: Operating System :: OS Independent
Classifier: Natural Language :: English
Requires-Python: >=3.10
License-File: LICENSE
Requires-Dist: dipamkara
Requires-Dist: colorama>=0.4.6
Requires-Dist: argparse>=1.4.0
Requires-Dist: PyYAML>=6.0.2
